soundcloudpy/__init__.py
soundcloudpy/const.py
soundcloudpy/soundcloudpy.py
soundcloudpy-0.1.4.dist-info/licenses/LICENCE
soundcloudpy-0.1.4.dist-info/METADATA
soundcloudpy-0.1.4.dist-info/WHEEL
soundcloudpy-0.1.4.dist-info/top_level.txt
soundcloudpy-0.1.4.dist-info/RECORD
