Metadata-Version: 2.4
Name: soundcloudpy
Version: 0.1.4
Summary: Client for async connection to the Soundcloud api.
Author-email: Giel Janssens <giel@music-assistant.io>
License: Apache-2.0
Platform: any
Classifier: Environment :: Console
Classifier: Programming Language :: Python :: 3.12
Classifier: Programming Language :: Python :: 3.13
Requires-Python: >=3.12
License-File: LICENCE
Requires-Dist: aiohttp>=3.12.0
Provides-Extra: test
Requires-Dist: black==25.1.0; extra == "test"
Requires-Dist: codespell==2.4.1; extra == "test"
Requires-Dist: isort==6.0.1; extra == "test"
Requires-Dist: mypy==1.16.1; extra == "test"
Requires-Dist: pre-commit==4.2.0; extra == "test"
Requires-Dist: pre-commit-hooks==5.0.0; extra == "test"
Requires-Dist: pylint==3.3.7; extra == "test"
Requires-Dist: pytest==8.4.1; extra == "test"
Requires-Dist: pytest-aiohttp==1.1.0; extra == "test"
Requires-Dist: pytest-cov==6.2.1; extra == "test"
Requires-Dist: ruff==0.12.2; extra == "test"
Requires-Dist: safety==3.5.2; extra == "test"
Dynamic: license-file
